{
  "Andriushchenko2020Understanding": 2000,
  "Carmon2019Unlabeled": 500,
  "Sehwag2020Hydra": 500,
  "Wang2020Improving": 500,
  "Hendrycks2019Using": 500,
  "Rice2020Overfitting": 200,
  "Zhang2019Theoretically": 400,
  "Engstrom2019Robustness": 400,
  "Chen2020Adversarial": 100,
  "Huang2020Self": 300,
  "Pang2020Boosting": 200,
  "Wong2020Fast": 2000,
  "Ding2020MMA": 1000,
  "Zhang2019You": 400,
  "Zhang2020Attacks": 400,
  "Wu2020Adversarial_extra": 500,
  "Wu2020Adversarial": 350,
  "Gowal2020Uncovering_70_16": 50,
  "Gowal2020Uncovering_70_16_extra": 50,
  "Gowal2020Uncovering_34_20": 100,
  "Gowal2020Uncovering_28_10_extra": 300,
  "Sehwag2021Proxy": 400,
  "Sehwag2021Proxy_R18": 1500,
  "Sitawarin2020Improving": 400,
  "Chen2020Efficient": 400,
  "Cui2020Learnable_34_20": 150,
  "Cui2020Learnable_34_10": 400,
  "Zhang2020Geometry": 500,
  "Rebuffi2021Fixing_28_10_cutmix_ddpm": 300,
  "Rebuffi2021Fixing_106_16_cutmix_ddpm": 50,
  "Rebuffi2021Fixing_70_16_cutmix_ddpm": 50,
  "Rebuffi2021Fixing_70_16_cutmix_extra": 50,
  "Sridhar2021Robust": 400,
  "Sridhar2021Robust_34_15": 300,
  "Rebuffi2021Fixing_R18_ddpm": 1000,
  "Rade2021Helper_R18_extra": 1000,
  "Rade2021Helper_R18_ddpm": 1000,
  "Rade2021Helper_extra": 250,
  "Rade2021Helper_ddpm": 300,
  "Huang2021Exploring": 100,
  "Huang2021Exploring_ema": 200,
  "Gowal2021Improving_70_16_ddpm_100m": 50
}